open_lora/__init__.py
open_lora/client.py
open_lora/pip install pydantic.py
open_lora/types.py
openlora_client-0.6.3.dist-info/METADATA
openlora_client-0.6.3.dist-info/WHEEL
openlora_client-0.6.3.dist-info/RECORD
