Metadata-Version: 2.3
Name: openlora-client
Version: 0.6.3
Summary: Open-Lora Python Client
License: Apache-2.0
Author: Arunmozhi
Author-email: arunmoxhi@openledger.xyz
Requires-Python: >=3.8,<4.0
Classifier: License :: OSI Approved :: Apache Software License
Classifier: Programming Language :: Python :: 3
Classifier: Programming Language :: Python :: 3.8
Classifier: Programming Language :: Python :: 3.9
Classifier: Programming Language :: Python :: 3.10
Classifier: Programming Language :: Python :: 3.11
Classifier: Programming Language :: Python :: 3.12
Classifier: Programming Language :: Python :: 3.13
Requires-Dist: aiohttp (>=3.9,<4.0)
Requires-Dist: certifi (==2024.7.4)
Requires-Dist: huggingface-hub (>=0.12,<1.0)
Requires-Dist: pydantic (>2,<3)
Project-URL: Homepage, https://github.com/openledger/open-lora
Project-URL: Repository, https://github.com/openledger/open-lora
